{
  "basics":{
    "photo":"index.jpg",
    "name":"syeda misba fathima",
    "email":"fathimasyedamisba@gmail.com",
    "phone":"9985412559",
    "address":"kurnool"
  },
"education":[
  {
"course":"B.tech(cse)",
"college":[
  "RCEW",
  "2015-2019",
  "71%"
]
},
{
"course":"Intermediate(Mpc)",
"college":[
"sri chaitanya",
"2013-2015",
"91%"
]
},
{
"course":"SSC",
"college":[
"Trinity eng medium high school",
"2013",
"87%"
]
}
],
"skills":[
  {
    "name":"operating system",
    "value":"windows,linux"
  },
  {
    "name":"Programming languages",
    "value":"c,c++,java"
  },
  {
    "name":"web development",
    "value":"HTML,PHP,.net"
  }
]
}
